[{ "type": "result", "timestamp": "2023-04-12T08:06:21Z", "ping": { "jitter": 165.163, "latency": 143.282, "low": 74.221, "high": 422.844 }, "download": { "bandwidth": 3530461, "bytes": 37138100, "elapsed": 11605, "latency": { "iqm": 310.561, "low": 78.347, "high": 1118.430, "jitter": 74.074 } }, "upload": { "bandwidth": 239021, "bytes": 2660728, "elapsed": 14868, "latency": { "iqm": 890.556, "low": 103.173, "high": 1308.041, "jitter": 116.461 } }, "packetLoss": 0, "isp": "31173 Services AB", "interface": { "internalIp": "10.111.140.152", "name": "utun6", "macAddr": "00:00:00:00:00:00", "isVpn": true, "externalIp": "193.32.126.237" }, "server": { "id": 4302, "host": "speedtest.vodafone.it", "port": 8080, "name": "Vodafone IT", "location": "Milan", "country": "Italy", "ip": "217.171.46.93" }, "result": { "id": "a0d48eef-2bd7-4cde-86a5-3c9d292fa2db", "url": "https://www.speedtest.net/result/c/a0d48eef-2bd7-4cde-86a5-3c9d292fa2db", "persisted": true } },{ "type": "result", "timestamp": "2023-04-12T08:06:55Z", "ping": { "jitter": 30.731, "latency": 95.353, "low": 80.468, "high": 134.404 }, "download": { "bandwidth": 1840681, "bytes": 18997180, "elapsed": 15006, "latency": { "iqm": 998.461, "low": 96.657, "high": 5569.145, "jitter": 91.305 } }, "upload": { "bandwidth": 210844, "bytes": 2634712, "elapsed": 14951, "latency": { "iqm": 1522.823, "low": 89.218, "high": 4319.132, "jitter": 94.792 } }, "packetLoss": 1.056338028169014, "isp": "31173 Services AB", "interface": { "internalIp": "10.111.140.152", "name": "utun6", "macAddr": "00:00:00:00:00:00", "isVpn": true, "externalIp": "193.32.126.237" }, "server": { "id": 4302, "host": "speedtest.vodafone.it", "port": 8080, "name": "Vodafone IT", "location": "Milan", "country": "Italy", "ip": "217.171.46.93" }, "result": { "id": "2ef4ad20-e50b-4e07-a946-930a58403c04", "url": "https://www.speedtest.net/result/c/2ef4ad20-e50b-4e07-a946-930a58403c04", "persisted": true } }]
